ripiu/cmsplugin_articles/__init__.py
ripiu/cmsplugin_articles/apps.py
ripiu/cmsplugin_articles/cms_plugins.py
ripiu/cmsplugin_articles/conf.py
ripiu/cmsplugin_articles/models.py
ripiu/cmsplugin_articles/locale/it/LC_MESSAGES/django.mo
ripiu/cmsplugin_articles/locale/it/LC_MESSAGES/django.po
ripiu/cmsplugin_articles/migrations/0001_initial.py
ripiu/cmsplugin_articles/migrations/0002_auto_20171207_1123.py
ripiu/cmsplugin_articles/migrations/0003_auto_20171207_1310.py
ripiu/cmsplugin_articles/migrations/0004_auto_20171213_1327.py
ripiu/cmsplugin_articles/migrations/0005_auto_20180222_1207.py
ripiu/cmsplugin_articles/migrations/0006_auto_20180222_1419.py
ripiu/cmsplugin_articles/migrations/0007_field_names.py
ripiu/cmsplugin_articles/migrations/__init__.py
ripiu/cmsplugin_articles/migrations/__pycache__/0001_initial.cpython-35.pyc
ripiu/cmsplugin_articles/migrations/__pycache__/0001_initial.cpython-36.pyc
ripiu/cmsplugin_articles/migrations/__pycache__/0002_auto_20171207_1123.cpython-35.pyc
ripiu/cmsplugin_articles/migrations/__pycache__/0002_auto_20171207_1123.cpython-36.pyc
ripiu/cmsplugin_articles/migrations/__pycache__/0003_auto_20171207_1310.cpython-35.pyc
ripiu/cmsplugin_articles/migrations/__pycache__/0003_auto_20171207_1310.cpython-36.pyc
ripiu/cmsplugin_articles/migrations/__pycache__/0004_auto_20171213_1327.cpython-35.pyc
ripiu/cmsplugin_articles/migrations/__pycache__/0004_auto_20171213_1327.cpython-36.pyc
ripiu/cmsplugin_articles/migrations/__pycache__/0005_auto_20180222_1207.cpython-35.pyc
ripiu/cmsplugin_articles/migrations/__pycache__/0005_auto_20180222_1207.cpython-36.pyc
ripiu/cmsplugin_articles/migrations/__pycache__/0006_auto_20180222_1419.cpython-35.pyc
ripiu/cmsplugin_articles/migrations/__pycache__/0006_auto_20180222_1419.cpython-36.pyc
ripiu/cmsplugin_articles/migrations/__pycache__/0007_field_names.cpython-35.pyc
ripiu/cmsplugin_articles/migrations/__pycache__/__init__.cpython-35.pyc
ripiu.cmsplugin_articles-0.4.2.dist-info/AUTHORS
ripiu.cmsplugin_articles-0.4.2.dist-info/LICENSE
ripiu.cmsplugin_articles-0.4.2.dist-info/METADATA
ripiu.cmsplugin_articles-0.4.2.dist-info/WHEEL
ripiu.cmsplugin_articles-0.4.2.dist-info/top_level.txt
ripiu.cmsplugin_articles-0.4.2.dist-info/RECORD
