Metadata-Version: 2.1
Name: ripiu.cmsplugin-articles
Version: 0.4.2
Summary: Articles
Home-page: https://github.com/ripiu/cmsplugin_articles
Author: matteo vezzola
Author-email: matteo@studioripiu.it
License: BSD-new
Platform: UNKNOWN
Classifier: Development Status :: 3 - Alpha
Classifier: Framework :: Django
Classifier: Intended Audience :: Developers
Classifier: License :: OSI Approved :: BSD License
Classifier: Operating System :: OS Independent
Classifier: Programming Language :: Python
Classifier: Topic :: Internet :: WWW/HTTP :: Dynamic Content
Requires-Python: >=3.3
Requires-Dist: Django (>=1.11)
Requires-Dist: django-cms (>=3.5.0)
Requires-Dist: djangocms-attributes-field (>=0.1.1)
Requires-Dist: django-appconf
Requires-Dist: django-model-mixins (>=1.0.4)
